CONTRIBUTING.rst
HISTORY.rst
LICENSE
MANIFEST.in
README.rst
setup.cfg
setup.py
advertest/__init__.py
advertest/ad_create.py
advertest/ad_from_string.py
advertest/cli.py
advertest/kw_generate.py
advertest/stopwords.py
advertest/url_builders.py
advertest/word_frequency.py
advertest.egg-info/PKG-INFO
advertest.egg-info/SOURCES.txt
advertest.egg-info/dependency_links.txt
advertest.egg-info/entry_points.txt
advertest.egg-info/not-zip-safe
advertest.egg-info/requires.txt
advertest.egg-info/top_level.txt
docs/Makefile
docs/advertest.rst
docs/conf.py
docs/contributing.rst
docs/history.rst
docs/index.rst
docs/installation.rst
docs/make.bat
docs/modules.rst
docs/readme.rst
docs/usage.rst
docs/_build/html/_static/ajax-loader.gif
docs/_build/html/_static/comment-bright.png
docs/_build/html/_static/comment-close.png
docs/_build/html/_static/comment.png
docs/_build/html/_static/down-pressed.png
docs/_build/html/_static/down.png
docs/_build/html/_static/file.png
docs/_build/html/_static/minus.png
docs/_build/html/_static/plus.png
docs/_build/html/_static/up-pressed.png
docs/_build/html/_static/up.png
tests/test_ad_create.py
tests/test_advertest.py
tests/test_kw_generate.py