Metadata-Version: 1.1
Name: advertest
Version: 1.0.1
Summary: Productivity and analysis tools for online marketing
Home-page: https://github.com/eliasdabbas/advertest
Author: Elias Dabbas
Author-email: eliasdabbas@gmail.com
License: MIT license
Keywords: advertising marketing search-engine-optimization adwordsseo sem bingads keyword-research
Platform: UNKNOWN
Classifier: Development Status :: 4 - Beta
Classifier: Intended Audience :: Developers
Classifier: Intended Audience :: End Users/Desktop
Classifier: License :: OSI Approved :: MIT License
Classifier: Natural Language :: English
Classifier: Programming Language :: Python :: 2
Classifier: Programming Language :: Python :: 2.7
Classifier: Programming Language :: Python :: 3
Classifier: Programming Language :: Python :: 3.4
Classifier: Programming Language :: Python :: 3.5
Classifier: Programming Language :: Python :: 3.6
